ddpg_agent/__init__.py
ddpg_agent/agent.py
ddpg_agent/models.py
ddpg_agent/visualizations.py
ddpg_agent-0.0.2.dist-info/LICENSE
ddpg_agent-0.0.2.dist-info/METADATA
ddpg_agent-0.0.2.dist-info/WHEEL
ddpg_agent-0.0.2.dist-info/top_level.txt
ddpg_agent-0.0.2.dist-info/RECORD
