Metadata-Version: 2.1
Name: ddpg-agent
Version: 0.0.2
Summary: Reinforcement Learning model using Deep Deterministic Policy Gradients (DDPG)
Home-page: https://github.com/samhiatt/ddpg_agent
Author: Sam Hiatt
Author-email: samhiatt@gmail.com
License: MIT
Platform: UNKNOWN
Classifier: Programming Language :: Python :: 3
Classifier: License :: OSI Approved :: MIT License
Classifier: Operating System :: OS Independent
Requires-Dist: imageio-ffmpeg (==0.3.0)
Requires-Dist: tensorflow (==1.13.1)
Requires-Dist: keras (==2.2.4)
